monty/__init__.py
monty/monty.py
montemplate-3.0.0.dist-info/LICENSE
montemplate-3.0.0.dist-info/METADATA
montemplate-3.0.0.dist-info/WHEEL
montemplate-3.0.0.dist-info/entry_points.txt
montemplate-3.0.0.dist-info/top_level.txt
montemplate-3.0.0.dist-info/RECORD
