Metadata-Version: 2.1
Name: montemplate
Version: 3.0.0
Summary: Python project generator.
Home-page: https://github.com/lycantropos/monty/
Download-URL: https://github.com/lycantropos/monty/archive/master.zip
Author: Azat Ibrakov
Author-email: azatibrakov@gmail.com
License: MIT License
Classifier: Intended Audience :: Developers
Classifier: License :: OSI Approved :: MIT License
Classifier: Programming Language :: Python :: 3.6
Classifier: Programming Language :: Python :: 3.7
Classifier: Programming Language :: Python :: 3.8
Classifier: Programming Language :: Python :: 3.9
Classifier: Programming Language :: Python :: 3.10
Classifier: Programming Language :: Python :: Implementation :: CPython
Classifier: Programming Language :: Python :: Implementation :: PyPy
Requires-Python: >=3.6
License-File: LICENSE
Requires-Dist: click (<9.0,>=8.0.4)
Requires-Dist: jinja2 (<4.0,>=3.0.3)
Requires-Dist: requests (<3.0.0,>=2.27.1)
Requires-Dist: strictyaml (<2.0.0,>=1.6.1)
